asc_analyzer/__init__.py
asc_analyzer/cli.py
asc_analyzer/core.py
asc_analyzer/data/allFreqsCOW_Refined_20240315.json
asc_analyzer/data/allFreqsSubT_20240305.json
asc_analyzer/data/ascSoaCOW_20240305.json
asc_analyzer/data/ascSoaSubT_20240305.json
asc_analyzer-0.0.9.dist-info/METADATA
asc_analyzer-0.0.9.dist-info/WHEEL
asc_analyzer-0.0.9.dist-info/entry_points.txt
asc_analyzer-0.0.9.dist-info/top_level.txt
asc_analyzer-0.0.9.dist-info/RECORD
