Metadata-Version: 2.4
Name: asc-analyzer
Version: 0.0.9
Summary: asc-analyzer
Home-page: https://github.com/hksung/ASC-analyzer
Author: Hakyung Sung
Author-email: hksung001@gmail.com
License: CC-BY-NC-SA-4.0
Classifier: Programming Language :: Python :: 3
Classifier: Operating System :: OS Independent
Requires-Python: >=3.7
Dynamic: author
Dynamic: author-email
Dynamic: summary
